text_eval_benchmark/__init__.py
text_eval_benchmark/text_similarity.py
text_eval_benchmark-0.1.0.dist-info/LICENSE
text_eval_benchmark-0.1.0.dist-info/METADATA
text_eval_benchmark-0.1.0.dist-info/WHEEL
text_eval_benchmark-0.1.0.dist-info/top_level.txt
text_eval_benchmark-0.1.0.dist-info/RECORD
